Metadata-Version: 2.1
Name: amirhoshein
Version: 1.4.4
Summary: amirhoshein library test
Home-page: UNKNOWN
Author: amir_hoshein
Author-email: a.gaffarzadeh.1387.2@gmail.com
License: UNKNOWN
Keywords: python
Platform: UNKNOWN
Classifier: Development Status :: 1 - Planning
Classifier: Intended Audience :: Developers
Classifier: Programming Language :: Python :: 3
Classifier: Operating System :: Unix
Classifier: Operating System :: MacOS :: MacOS X
Classifier: Operating System :: Microsoft :: Windows
